popx_tools/__init__.py
popx_tools/cli.py
popx_tools/install/__init__.py
popx_tools/install/laya.py
popx_tools/install/node.py
popx_tools/install/npm.py
popx_tools/install/nvm.py
popx_tools/install/popxcmd.py
popx_tools/install/bin/node-v10.24.1-win-x64.zip
popx_tools/install/bin/npm-6.14.12.tgz
popx_tools/install/bin/nvm-setup.exe
popx_tools/ui/__init__.py
popx_tools/uninstall/__init__.py
popx_tools-1.0.5.dist-info/licenses/LICENSE
popx_tools-1.0.5.dist-info/METADATA
popx_tools-1.0.5.dist-info/WHEEL
popx_tools-1.0.5.dist-info/entry_points.txt
popx_tools-1.0.5.dist-info/top_level.txt
popx_tools-1.0.5.dist-info/RECORD
